README
setup.py
climesync/__init__.py
climesync/climesync.py
climesync/commands.py
climesync/util.py
climesync.egg-info/PKG-INFO
climesync.egg-info/SOURCES.txt
climesync.egg-info/dependency_links.txt
climesync.egg-info/entry_points.txt
climesync.egg-info/requires.txt
climesync.egg-info/top_level.txt
testing/__init__.py
testing/test_climesync.py
testing/test_commands.py
testing/test_data.py
testing/test_scripting.py
testing/test_util.py