Metadata-Version: 1.1
Name: climesync
Version: 0.1.1
Summary: Climesync - CLI Frontend for the OSUOSL TimeSync API
Home-page: https://github.com/osuosl/climesync
Author: OSU Open Source Lab
Author-email: support@osuosl.org
License: Apache Version 2.0
Keywords: timesync pymesync cli frontend
Platform: UNKNOWN
Classifier: Development Status :: 4 - Beta
Classifier: License :: OSI Approved :: Apache Software License
Classifier: Programming Language :: Python :: 2.7
